{
    "configurations": [
        {
            "name": "Linux",
            "includePath": [
                "${workspaceFolder}/src/**",
                "/usr/include/c++/8",
                "/usr/include/arm-linux-gnueabihf/c++/8"
            ],
            "defines": [
                "PLATFORM_BBB",
                "PLATFORM_PI"
            ],
            "compilerPath": "/usr/bin/g++",
            "cStandard": "gnu17",
            "cppStandard": "gnu++20",
            "intelliSenseMode": "linux-gcc-arm"
        }
    ],
    "version": 4
}